msal_bearer/__init__.py
msal_bearer/authenticator.py
msal_bearer/bearerauth.py
msal_bearer-1.4.3.dist-info/LICENSE.md
msal_bearer-1.4.3.dist-info/METADATA
msal_bearer-1.4.3.dist-info/WHEEL
msal_bearer-1.4.3.dist-info/RECORD
