Metadata-Version: 2.3
Name: msal-bearer
Version: 1.4.3
Summary: Python package to get auth token for a msal client application using msal, msal-extensions and azure-identity.
License: MIT
Author: Åsmund Våge Fannemel
Author-email: asmf@equinor.com
Requires-Python: >=3.9.2,<4.0.0
Classifier: License :: OSI Approved :: MIT License
Classifier: Operating System :: OS Independent
Classifier: Programming Language :: Python :: 3
Classifier: Programming Language :: Python :: 3.10
Classifier: Programming Language :: Python :: 3.11
Classifier: Programming Language :: Python :: 3.12
Classifier: Programming Language :: Python :: 3.13
Requires-Dist: azure-identity (>=1.24.0,<2.0.0)
Requires-Dist: cryptography (>=43.0.3)
Requires-Dist: msal (>=1.33.0,<2.0.0)
Requires-Dist: msal-extensions (>=1.3.1,<2.0.0)
Project-URL: Repository, https://github.com/Equinor/msal-bearer
